CHANGES.rst
LICENSE
MANIFEST.in
README.rst
requirements.txt
setup.py
django_textformat/__init__.py
django_textformat/admin.py
django_textformat/apps.py
django_textformat/modelfields.py
django_textformat/models.py
django_textformat/registry.py
django_textformat/signal_handlers.py
django_textformat/tests.py
django_textformat/text_filters.py
django_textformat/utils.py
django_textformat.egg-info/PKG-INFO
django_textformat.egg-info/SOURCES.txt
django_textformat.egg-info/dependency_links.txt
django_textformat.egg-info/not-zip-safe
django_textformat.egg-info/top_level.txt
django_textformat/migrations/0001_initial.py
django_textformat/migrations/__init__.py
django_textformat/templatetags/__init__.py
django_textformat/templatetags/textformats.py
tests/__init__.py
tests/models.py
tests/requirements.txt
tests/settings.py
tests/test_imports.py