Metadata-Version: 1.1
Name: django-textformat
Version: 0.1.0
Summary: Provides a TextFormatField for Django models and allows to build text formats out of simple filters.
Home-page: https://github.com/team23/django_textformat
Author: David Danier
Author-email: david.danier@team23.de
License: BSD licence, see LICENSE file
Platform: UNKNOWN
Classifier: Development Status :: 4 - Beta
Classifier: Environment :: Web Environment
Classifier: Framework :: Django
Classifier: Framework :: Django :: 1.8
Classifier: Intended Audience :: Developers
Classifier: License :: OSI Approved :: BSD License
Classifier: Natural Language :: English
Classifier: Programming Language :: Python
Classifier: Programming Language :: Python :: 2
Classifier: Programming Language :: Python :: 2.7
Classifier: Programming Language :: Python :: 3.5
